ndsi-1.4.5.dist-info/RECORD
ndsi-1.4.5.dist-info/LICENSE
ndsi-1.4.5.dist-info/WHEEL
ndsi-1.4.5.dist-info/top_level.txt
ndsi-1.4.5.dist-info/METADATA
ndsi/writer.cpython-37m-darwin.so
ndsi/frame.pxd
ndsi/writer.pyx
ndsi/formatter.py
ndsi/frame.cpp
ndsi/sensor.py
ndsi/frame.cpython-37m-darwin.so
ndsi/__init__.py
ndsi/cturbojpeg.pxd
ndsi/h264.pxd
ndsi/network.py
ndsi/writer.pxd
ndsi/writer.cpp
ndsi/frame.pyx
ndsi/h264/utilbase.h
ndsi/h264/ffmpeg_utils.h
ndsi/h264/mp4_writer.cpp
ndsi/h264/h264_utils.h
ndsi/h264/h264_decoder.cpp
ndsi/h264/media_stream.cpp
ndsi/h264/localdefines.h
ndsi/h264/h264_utils.cpp
ndsi/h264/media_stream.h
ndsi/h264/h264_decoder.h
ndsi/h264/video_stream.h
ndsi/h264/mp4_writer.h
ndsi/h264/ffmpeg_utils.cpp
ndsi/h264/video_stream.cpp
ndsi/h264/windows/unistd.h
ndsi/h264/windows/getopt.h
ndsi/h264/windows/getopt.cpp
ndsi/.dylibs/libtheoraenc.1.dylib
ndsi/.dylibs/libvpx.7.dylib
ndsi/.dylibs/libavformat.59.27.100.dylib
ndsi/.dylibs/libaom.3.2.0.dylib
ndsi/.dylibs/libxml2.2.dylib
ndsi/.dylibs/libvorbisenc.2.dylib
ndsi/.dylibs/libdav1d.5.dylib
ndsi/.dylibs/libx264.164.dylib
ndsi/.dylibs/libX11.6.dylib
ndsi/.dylibs/libtheoradec.1.dylib
ndsi/.dylibs/libtwolame.0.dylib
ndsi/.dylibs/libpng16.16.dylib
ndsi/.dylibs/libmp3lame.0.dylib
ndsi/.dylibs/libxcb.1.1.0.dylib
ndsi/.dylibs/libfreetype.6.dylib
ndsi/.dylibs/libavcodec.59.37.100.dylib
ndsi/.dylibs/libswresample.4.7.100.dylib
ndsi/.dylibs/libx265.199.dylib
ndsi/.dylibs/libopencore-amrnb.0.dylib
ndsi/.dylibs/libopenjp2.2.4.0.dylib
ndsi/.dylibs/libXdmcp.6.dylib
ndsi/.dylibs/libfontconfig.1.dylib
ndsi/.dylibs/libswscale.6.7.100.dylib
ndsi/.dylibs/libXau.6.dylib
ndsi/.dylibs/libvorbis.0.dylib
ndsi/.dylibs/liblzma.5.dylib
ndsi/.dylibs/libspeex.1.dylib
ndsi/.dylibs/libopencore-amrwb.0.dylib
ndsi/.dylibs/libbluray.2.dylib
ndsi/.dylibs/libgmp.10.dylib
ndsi/.dylibs/libavutil.57.28.100.dylib
ndsi/.dylibs/libogg.0.dylib
ndsi/.dylibs/libturbojpeg.0.dylib
ndsi/.dylibs/libopus.0.dylib
