Metadata-Version: 2.1
Name: ndsi
Version: 1.4.5
Summary: "Remote Device Sensor Interface"
Home-page: https://github.com/pupil-labs/pyndsi
Author: "Pupil Labs"
Author-email: "info@pupil-labs.com"
License: LGPL-3.0
Project-URL: Changelog, https://github.com/pupil-labs/pyndsi/blob/master/CHANGELOG.md
Classifier: Development Status :: 5 - Production/Stable
Classifier: Intended Audience :: Developers
Classifier: License :: OSI Approved :: GNU Lesser General Public License v3 (LGPLv3)
Classifier: Natural Language :: English
Classifier: Programming Language :: Python :: 3
Classifier: Programming Language :: Python :: 3 :: Only
Classifier: Programming Language :: Python :: Implementation :: CPython
Classifier: Topic :: System :: Networking
Requires-Python: >=3.6
Provides-Extra: dev
License-File: LICENSE
